MANIFEST.in
README.rst
setup.py
cython_csg/__init__.py
cython_csg/_cython_csg.pyx
cython_csg/cython_csg.c
cython_csg.egg-info/PKG-INFO
cython_csg.egg-info/SOURCES.txt
cython_csg.egg-info/dependency_links.txt
cython_csg.egg-info/not-zip-safe
cython_csg.egg-info/requires.txt
cython_csg.egg-info/top_level.txt