Metadata-Version: 1.1
Name: cython-csg
Version: 0.5.8
Summary: Constructive solid geometry on meshes using BSP trees in Cython CSG.
Home-page: https://github.com/tomturner/cython-csg
Author: Thomas Turner
Author-email: tom@twt.me.uk
License: MIT
Platform: UNKNOWN
Classifier: Development Status :: 5 - Production/Stable
Classifier: Environment :: Web Environment
Classifier: License :: OSI Approved :: MIT License
Classifier: Framework :: Django
Classifier: Framework :: Django :: 2.0
Classifier: Programming Language :: Python
Classifier: Programming Language :: Python :: 3.4
Classifier: Programming Language :: Python :: 3.5
Classifier: Programming Language :: Python :: 3.6
Classifier: Topic :: Software Development :: Libraries :: Python Modules
